django_renderpdf/__init__.py
django_renderpdf/helpers.py
django_renderpdf/version.py
django_renderpdf/views.py
django_renderpdf-6.0.0.dist-info/LICENCE
django_renderpdf-6.0.0.dist-info/METADATA
django_renderpdf-6.0.0.dist-info/WHEEL
django_renderpdf-6.0.0.dist-info/top_level.txt
django_renderpdf-6.0.0.dist-info/RECORD
