Metadata-Version: 2.1
Name: django-renderpdf
Version: 6.0.0
Summary: Django app to render django templates as PDF files.
Author-email: Hugo Osvaldo Barrera <hugo@whynothugo.nl>
License: ISC
Project-URL: repository, https://github.com/WhyNotHugo/django-renderpdf/
Project-URL: documentation, https://django-renderpdf.readthedocs.io/
Project-URL: changelog, https://github.com/WhyNotHugo/django-renderpdf/blob/main/CHANGELOG.rst
Project-URL: issues, https://github.com/WhyNotHugo/django-renderpdf/issues/
Project-URL: funding, https://whynothugo.nl/sponsor/
Keywords: django,weasyprint,pdf
Classifier: Development Status :: 6 - Mature
Classifier: Environment :: Web Environment
Classifier: Framework :: Django
Classifier: Framework :: Django :: 4.2
Classifier: Framework :: Django :: 5.1
Classifier: Framework :: Django :: 5.2
Classifier: License :: OSI Approved :: ISC License (ISCL)
Classifier: Operating System :: OS Independent
Classifier: Programming Language :: Python :: 3
Classifier: Programming Language :: Python :: 3.10
Classifier: Programming Language :: Python :: 3.11
Classifier: Programming Language :: Python :: 3.12
Classifier: Programming Language :: Python :: 3.13
Classifier: Programming Language :: Python :: 3.14
Classifier: Topic :: Internet :: WWW/HTTP
Classifier: Topic :: Software Development :: Libraries :: Python Modules
Requires-Python: >=3.10
License-File: LICENCE
Requires-Dist: django >=4.2
Requires-Dist: weasyprint <68,>=63
Provides-Extra: docs
Requires-Dist: sphinx ; extra == 'docs'
Provides-Extra: lint
Requires-Dist: ruff ; extra == 'lint'
Requires-Dist: mypy ; extra == 'lint'
Requires-Dist: django-stubs ; extra == 'lint'
